skgenome/__init__.py
scikit_genome-0.0.1.dist-info/METADATA
scikit_genome-0.0.1.dist-info/WHEEL
scikit_genome-0.0.1.dist-info/top_level.txt
scikit_genome-0.0.1.dist-info/RECORD
