Metadata-Version: 2.1
Name: scikit-genome
Version: 0.0.1
Summary: A Python package for genomics
Home-page: https://github.com/scikit-genome/scikit-genome
Author: Allen Goodman
Author-email: allen.goodman@icloud.com
License: UNKNOWN
Project-URL: Bug Reports, https://github.com/scikit-genome/scikit-genome/issues
Project-URL: Source, https://github.com/scikit-genome/scikit-genome/
Platform: UNKNOWN
Classifier: Development Status :: 1 - Planning
Classifier: Intended Audience :: Science/Research
Classifier: License :: OSI Approved :: MIT License
Classifier: Programming Language :: Python :: 3
Classifier: Programming Language :: Python :: 3.7
Classifier: Programming Language :: Python :: 3.8
Classifier: Topic :: Scientific/Engineering :: Bio-Informatics
Requires-Python: >=3.7, <4
Provides-Extra: build
Requires-Dist: twine (>=3.1.1) ; extra == 'build'
Provides-Extra: dev
Requires-Dist: black (>=19.10b0) ; extra == 'dev'
Requires-Dist: check-manifest (>=0.41) ; extra == 'dev'
Requires-Dist: pre-commit (>=2.2.0) ; extra == 'dev'
Provides-Extra: test
Requires-Dist: coverage (>=5.0.4) ; extra == 'test'
Requires-Dist: pytest (>=5.4.1) ; extra == 'test'
